odoo/addons/stock_valuation_layer_usage/README.rst
odoo/addons/stock_valuation_layer_usage/__init__.py
odoo/addons/stock_valuation_layer_usage/__manifest__.py
odoo/addons/stock_valuation_layer_usage/i18n/stock_valuation_layer_usage.pot
odoo/addons/stock_valuation_layer_usage/models/__init__.py
odoo/addons/stock_valuation_layer_usage/models/stock_move.py
odoo/addons/stock_valuation_layer_usage/models/stock_valuation_layer.py
odoo/addons/stock_valuation_layer_usage/models/stock_valuation_layer_usage.py
odoo/addons/stock_valuation_layer_usage/readme/CONTRIBUTORS.rst
odoo/addons/stock_valuation_layer_usage/readme/DESCRIPTION.rst
odoo/addons/stock_valuation_layer_usage/readme/HISTORY.rst
odoo/addons/stock_valuation_layer_usage/readme/INSTALL.rst
odoo/addons/stock_valuation_layer_usage/readme/USAGE.rst
odoo/addons/stock_valuation_layer_usage/security/ir.model.access.csv
odoo/addons/stock_valuation_layer_usage/static/description/icon.png
odoo/addons/stock_valuation_layer_usage/static/description/index.html
odoo/addons/stock_valuation_layer_usage/tests/__init__.py
odoo/addons/stock_valuation_layer_usage/tests/test_stock_valuation_layer_usage.py
odoo/addons/stock_valuation_layer_usage/views/stock_move_views.xml
odoo/addons/stock_valuation_layer_usage/views/stock_valuation_layer_usage_views.xml
odoo/addons/stock_valuation_layer_usage/views/stock_valuation_layer_views.xml
odoo14_addon_stock_valuation_layer_usage-14.0.1.0.1.dist-info/METADATA
odoo14_addon_stock_valuation_layer_usage-14.0.1.0.1.dist-info/WHEEL
odoo14_addon_stock_valuation_layer_usage-14.0.1.0.1.dist-info/top_level.txt
odoo14_addon_stock_valuation_layer_usage-14.0.1.0.1.dist-info/RECORD
